README.rst
flask_quik.py
setup.py
Flask_Quik.egg-info/PKG-INFO
Flask_Quik.egg-info/SOURCES.txt
Flask_Quik.egg-info/dependency_links.txt
Flask_Quik.egg-info/not-zip-safe
Flask_Quik.egg-info/requires.txt
Flask_Quik.egg-info/top_level.txt