Metadata-Version: 1.1
Name: Flask-Quik
Version: 0.1.1
Summary: Quik for Flask
Home-page: http://github.com/avelino/Flask-Quik
Author: Thiago Avelino
Author-email: thiago@avelino.xxx
License: MIT
Platform: any
Classifier: Development Status :: 4 - Beta
Classifier: Environment :: Web Environment
Classifier: Intended Audience :: Developers
Classifier: License :: OSI Approved :: MIT License
Classifier: Operating System :: OS Independent
Classifier: Programming Language :: Python
Classifier: Topic :: Internet :: WWW/HTTP :: Dynamic Content
Classifier: Topic :: Software Development :: Libraries :: Python Modules
